odoo/addons/base_multi_company/README.rst
odoo/addons/base_multi_company/__init__.py
odoo/addons/base_multi_company/__manifest__.py
odoo/addons/base_multi_company/hooks.py
odoo/addons/base_multi_company/i18n/base_multi_company.pot
odoo/addons/base_multi_company/i18n/es.po
odoo/addons/base_multi_company/i18n/fr.po
odoo/addons/base_multi_company/i18n/hr.po
odoo/addons/base_multi_company/i18n/nl_NL.po
odoo/addons/base_multi_company/i18n/pt.po
odoo/addons/base_multi_company/i18n/pt_BR.po
odoo/addons/base_multi_company/i18n/zh_CN.po
odoo/addons/base_multi_company/models/__init__.py
odoo/addons/base_multi_company/models/multi_company_abstract.py
odoo/addons/base_multi_company/models/res_company_assignment.py
odoo/addons/base_multi_company/readme/CONTRIBUTORS.rst
odoo/addons/base_multi_company/readme/DESCRIPTION.rst
odoo/addons/base_multi_company/readme/USAGE.rst
odoo/addons/base_multi_company/security/ir.model.access.csv
odoo/addons/base_multi_company/static/description/icon.png
odoo/addons/base_multi_company/static/description/index.html
odoo/addons/base_multi_company/tests/__init__.py
odoo/addons/base_multi_company/tests/test_multi_company_abstract.py
odoo/addons/base_multi_company/tests/test_res_company_assignment.py
odoo12_addon_base_multi_company-12.0.1.0.1.99.dev13.dist-info/METADATA
odoo12_addon_base_multi_company-12.0.1.0.1.99.dev13.dist-info/WHEEL
odoo12_addon_base_multi_company-12.0.1.0.1.99.dev13.dist-info/top_level.txt
odoo12_addon_base_multi_company-12.0.1.0.1.99.dev13.dist-info/RECORD
